{"errors":[],"warnings":[],"namedChunkGroups":{"polyfill":{"chunks":[3,0,13],"assets":["webpack-runtime-3a7f5d9a746e678d634c.js","webpack-runtime-3a7f5d9a746e678d634c.js.map","commons-cf46c50215bb02659613.js","commons-cf46c50215bb02659613.js.map","polyfill-2fec127eb16d520a9090.js","polyfill-2fec127eb16d520a9090.js.map"],"children":{},"childAssets":{}},"app":{"chunks":[3,12,4],"assets":["webpack-runtime-3a7f5d9a746e678d634c.js","webpack-runtime-3a7f5d9a746e678d634c.js.map","framework-cd3e1e804d552fa282ef.js","framework-cd3e1e804d552fa282ef.js.map","app-2f5420f28e6a5eb2b7cf.js","app-2f5420f28e6a5eb2b7cf.js.map"],"children":{},"childAssets":{}},"component---src-pages-404-js":{"chunks":[2,1,0,5],"assets":["styles.a43d96010514e0626668.css","styles-7d4153d260c0197f0043.js","styles-7d4153d260c0197f0043.js.map","1bfc9850-52edaaddd8416cbe7fae.js","1bfc9850-52edaaddd8416cbe7fae.js.map","commons-cf46c50215bb02659613.js","commons-cf46c50215bb02659613.js.map","component---src-pages-404-js-5b360cabf00a8c6858da.js","component---src-pages-404-js-5b360cabf00a8c6858da.js.map"],"children":{},"childAssets":{}},"component---src-pages-about-js":{"chunks":[2,1,0,6],"assets":["styles.a43d96010514e0626668.css","styles-7d4153d260c0197f0043.js","styles-7d4153d260c0197f0043.js.map","1bfc9850-52edaaddd8416cbe7fae.js","1bfc9850-52edaaddd8416cbe7fae.js.map","commons-cf46c50215bb02659613.js","commons-cf46c50215bb02659613.js.map","component---src-pages-about-js-712cbb594916de43c29a.js","component---src-pages-about-js-712cbb594916de43c29a.js.map"],"children":{},"childAssets":{}},"component---src-pages-contact-js":{"chunks":[2,1,0,7],"assets":["styles.a43d96010514e0626668.css","styles-7d4153d260c0197f0043.js","styles-7d4153d260c0197f0043.js.map","1bfc9850-52edaaddd8416cbe7fae.js","1bfc9850-52edaaddd8416cbe7fae.js.map","commons-cf46c50215bb02659613.js","commons-cf46c50215bb02659613.js.map","component---src-pages-contact-js-10fdbe7cab0d4a67eaa7.js","component---src-pages-contact-js-10fdbe7cab0d4a67eaa7.js.map"],"children":{},"childAssets":{}},"component---src-pages-imprint-js":{"chunks":[2,1,0,8],"assets":["styles.a43d96010514e0626668.css","styles-7d4153d260c0197f0043.js","styles-7d4153d260c0197f0043.js.map","1bfc9850-52edaaddd8416cbe7fae.js","1bfc9850-52edaaddd8416cbe7fae.js.map","commons-cf46c50215bb02659613.js","commons-cf46c50215bb02659613.js.map","component---src-pages-imprint-js-121d8ee61a375c96d060.js","component---src-pages-imprint-js-121d8ee61a375c96d060.js.map"],"children":{},"childAssets":{}},"component---src-pages-privacy-js":{"chunks":[2,1,0,9],"assets":["styles.a43d96010514e0626668.css","styles-7d4153d260c0197f0043.js","styles-7d4153d260c0197f0043.js.map","1bfc9850-52edaaddd8416cbe7fae.js","1bfc9850-52edaaddd8416cbe7fae.js.map","commons-cf46c50215bb02659613.js","commons-cf46c50215bb02659613.js.map","component---src-pages-privacy-js-6f1a265d6a74720f4cd4.js","component---src-pages-privacy-js-6f1a265d6a74720f4cd4.js.map"],"children":{},"childAssets":{}},"component---src-templates-blog-post-js":{"chunks":[2,1,0,10],"assets":["styles.a43d96010514e0626668.css","styles-7d4153d260c0197f0043.js","styles-7d4153d260c0197f0043.js.map","1bfc9850-52edaaddd8416cbe7fae.js","1bfc9850-52edaaddd8416cbe7fae.js.map","commons-cf46c50215bb02659613.js","commons-cf46c50215bb02659613.js.map","component---src-templates-blog-post-js-aae4bd235dbd2c55fa84.js","component---src-templates-blog-post-js-aae4bd235dbd2c55fa84.js.map"],"children":{},"childAssets":{}},"component---src-templates-index-page-js":{"chunks":[2,1,0,11],"assets":["styles.a43d96010514e0626668.css","styles-7d4153d260c0197f0043.js","styles-7d4153d260c0197f0043.js.map","1bfc9850-52edaaddd8416cbe7fae.js","1bfc9850-52edaaddd8416cbe7fae.js.map","commons-cf46c50215bb02659613.js","commons-cf46c50215bb02659613.js.map","component---src-templates-index-page-js-73ec8d77c6b9fafdb156.js","component---src-templates-index-page-js-73ec8d77c6b9fafdb156.js.map"],"children":{},"childAssets":{}}},"assetsByChunkName":{"polyfill":["webpack-runtime-3a7f5d9a746e678d634c.js","commons-cf46c50215bb02659613.js","polyfill-2fec127eb16d520a9090.js"],"app":["webpack-runtime-3a7f5d9a746e678d634c.js","framework-cd3e1e804d552fa282ef.js","app-2f5420f28e6a5eb2b7cf.js"],"component---src-pages-404-js":["styles.a43d96010514e0626668.css","styles-7d4153d260c0197f0043.js","1bfc9850-52edaaddd8416cbe7fae.js","commons-cf46c50215bb02659613.js","component---src-pages-404-js-5b360cabf00a8c6858da.js"],"component---src-pages-about-js":["styles.a43d96010514e0626668.css","styles-7d4153d260c0197f0043.js","1bfc9850-52edaaddd8416cbe7fae.js","commons-cf46c50215bb02659613.js","component---src-pages-about-js-712cbb594916de43c29a.js"],"component---src-pages-contact-js":["styles.a43d96010514e0626668.css","styles-7d4153d260c0197f0043.js","1bfc9850-52edaaddd8416cbe7fae.js","commons-cf46c50215bb02659613.js","component---src-pages-contact-js-10fdbe7cab0d4a67eaa7.js"],"component---src-pages-imprint-js":["styles.a43d96010514e0626668.css","styles-7d4153d260c0197f0043.js","1bfc9850-52edaaddd8416cbe7fae.js","commons-cf46c50215bb02659613.js","component---src-pages-imprint-js-121d8ee61a375c96d060.js"],"component---src-pages-privacy-js":["styles.a43d96010514e0626668.css","styles-7d4153d260c0197f0043.js","1bfc9850-52edaaddd8416cbe7fae.js","commons-cf46c50215bb02659613.js","component---src-pages-privacy-js-6f1a265d6a74720f4cd4.js"],"component---src-templates-blog-post-js":["styles.a43d96010514e0626668.css","styles-7d4153d260c0197f0043.js","1bfc9850-52edaaddd8416cbe7fae.js","commons-cf46c50215bb02659613.js","component---src-templates-blog-post-js-aae4bd235dbd2c55fa84.js"],"component---src-templates-index-page-js":["styles.a43d96010514e0626668.css","styles-7d4153d260c0197f0043.js","1bfc9850-52edaaddd8416cbe7fae.js","commons-cf46c50215bb02659613.js","component---src-templates-index-page-js-73ec8d77c6b9fafdb156.js"]}}